bgc_viewer/__init__.py
bgc_viewer/app.py
bgc_viewer/data_loader.py
bgc_viewer/database.py
bgc_viewer/file_utils.py
bgc_viewer/preprocessing.py
bgc_viewer/static/domain-colors.csv
bgc_viewer/static/index.html
bgc_viewer/static/assets/index-C72L-c3E.js
bgc_viewer/static/assets/index-DAv11KVZ.css
bgc_viewer/tests/conftest.py
bgc_viewer/tests/test_app.py
bgc_viewer/tests/test_data_loader.py
bgc_viewer/tests/test_integration.py
bgc_viewer/tests/test_preprocessing.py
bgc_viewer/tests/test_search.py
bgc_viewer-0.2.1.dist-info/METADATA
bgc_viewer-0.2.1.dist-info/WHEEL
bgc_viewer-0.2.1.dist-info/entry_points.txt
bgc_viewer-0.2.1.dist-info/RECORD
