Metadata-Version: 2.4
Name: bgc-viewer
Version: 0.2.1
Summary: A viewer to explore and visualize Biosynthetic Gene Cluster data
Author: Medema Group (see CITATION.cff for full citation)
License: Apache-2.0
Requires-Python: >=3.11
Requires-Dist: cachelib>=0.9.0
Requires-Dist: flask-cors>=4.0.0
Requires-Dist: flask-session>=0.5.0
Requires-Dist: flask>=2.3.0
Requires-Dist: ijson>=3.2.0
Requires-Dist: python-dotenv>=1.0.1
Requires-Dist: waitress>=3.0.0
Provides-Extra: dev
Requires-Dist: black>=23.0.0; extra == 'dev'
Requires-Dist: build>=0.10.0; extra == 'dev'
Requires-Dist: flake8>=6.0.0; extra == 'dev'
Requires-Dist: mypy>=1.0.0; extra == 'dev'
Requires-Dist: pytest>=7.0.0; extra == 'dev'
Requires-Dist: twine>=4.0.0; extra == 'dev'
Provides-Extra: redis
Requires-Dist: redis>=5.0.0; extra == 'redis'
